ssh_tunneler/__init__.py
ssh_tunneler/cli.py
ssh_tunneler/cloudflare.py
ssh_tunneler/config.py
ssh_tunneler/core.py
ssh_tunneler/ssh_utils.py
tunnelmate-1.1.0.dist-info/METADATA
tunnelmate-1.1.0.dist-info/WHEEL
tunnelmate-1.1.0.dist-info/entry_points.txt
tunnelmate-1.1.0.dist-info/top_level.txt
tunnelmate-1.1.0.dist-info/RECORD
