Metadata-Version: 2.4
Name: tunnelmate
Version: 1.1.0
Summary: Full-featured SSH tunnel & Cloudflare DNS management library and CLI
Author: Parsa Lakzian (with Tara AI)
Classifier: Programming Language :: Python :: 3
Classifier: License :: OSI Approved :: MIT License
Classifier: Operating System :: OS Independent
Requires-Python: >=3.7
Requires-Dist: requests
Requires-Dist: pyyaml
Dynamic: author
Dynamic: classifier
Dynamic: description
Dynamic: description-content-type
Dynamic: requires-dist
Dynamic: requires-python
Dynamic: summary
